{
  "CREATE_INSTANT_INVITE": "招待リンクの作成",
  "KICK_MEMBERS": "メンバーをキック",
  "BAN_MEMBERS": "メンバーをBAN",
  "ADMINISTRATOR": "管理者",
  "MANAGE_CHANNELS": "チャンネルの管理",
  "MANAGE_GUILD": "サーバー管理",
  "ADD_REACTIONS": "リアクションの追加",
  "VIEW_AUDIT_LOG": "監査ログの表示",
  "PRIORITY_SPEAKER": "優先スピーカー",
  "STREAM": "動画の配信",
  "VIEW_CHANNEL": "テキストチャンネルの閲覧＆ボイスチャンネルの表示",
  "SEND_MESSAGES": "メッセージの送信",
  "SEND_TTS_MESSAGES": "ttsメッセージの送信",
  "MANAGE_MESSAGES": "メッセージの管理",
  "EMBED_LINKS": "埋め込みリンクの送信",
  "ATTACH_FILES": "ファイルの送信",
  "READ_MESSAGE_HISTORY": "メッセージ履歴を表示",
  "MENTION_EVERYONE": "@everyone、@here、全てのロールにメンション",
  "USE_EXTERNAL_EMOJIS": "外部絵文字の使用",
  "VIEW_GUILD_INSIGHTS": "サーバーインサイトの表示",
  "CONNECT": "ボイスチャンネルへ接続",
  "SPEAK": "ボイスチャンネルで発言",
  "MUTE_MEMBERS": "メンバーをミュート",
  "DEAFEN_MEMBERS": "メンバーのスピーカーをミュート",
  "MOVE_MEMBERS": "メンバーを移動",
  "USE_VAD": "音声検出を使用",
  "CHANGE_NICKNAME": "ニックネームの変更",
  "MANAGE_NICKNAMES": "ニックネームの管理",
  "MANAGE_ROLES": "役職の管理",
  "MANAGE_WEBHOOKS": "WebHookの管理",
  "MANAGE_EMOJIS_AND_STICKERS": "絵文字の管理",
  "USE_APPLICATION_COMMANDS": "スラッシュコマンドの使用",
  "REQUEST_TO_SPEAK": "スピーカー参加をリクエスト",
  "MANAGE_THREADS": "スレッドの管理",
  "CREATE_PUBLIC_THREADS": "公開スレッドを作成",
  "CREATE_PRIVATE_THREADS": "プライベートスレッドの作成",
  "USE_EXTERNAL_STICKERS": "外部のステッカーの使用",
  "SEND_MESSAGES_IN_THREADS": "スレッドでメッセージを送信"
}